MANIFEST.in
README.md
requirements.txt
setup.cfg
setup.py
docs/advanced_features.md
docs/api_test_demo_app.md
docs/basic_features.md
docs/core_concepts.md
docs/environment_management.md
docs/index.md
docs/installation.md
docs/layered_structure.md
docs/plugin_dev.md
docs/quick_start.md
docs/testcase_generator.md
notest/__init__.py
notest/common_test.py
notest/config_loader.py
notest/contenthandling.py
notest/context.py
notest/generators.py
notest/main.py
notest/master.py
notest/notest_lib.py
notest/operations.py
notest/plugin_registery.py
notest/test_result.py
notest/test_runners.py
notest/testset.py
notest/validators.py
notest/yaml_test.py
notest.egg-info/PKG-INFO
notest.egg-info/SOURCES.txt
notest.egg-info/dependency_links.txt
notest.egg-info/entry_points.txt
notest.egg-info/requires.txt
notest.egg-info/top_level.txt
notest.egg-info/zip-safe
notest/clients/__init__.py
notest/clients/http_auth_type.py
notest/clients/http_response.py
notest/clients/pycurl_client.py
notest/clients/request_client.py
notest/clients/requests_client.py
notest/ext/__init__.py
notest/ext/extractor_jmespath.py
notest/ext/extractor_mysql.py
notest/ext/generator_csv.py
notest/ext/generator_mysql.py
notest/ext/operation_mysql_upsert.py
notest/ext/operation_print.py
notest/ext/operation_sleep.py
notest/ext/validator_jsonschema.py
notest/http_test_runner/__init__.py
notest/http_test_runner/http_test.py
notest/http_test_runner/http_test_exec.py
notest/lib/__init__.py
notest/lib/mysql_lib.py
notest/lib/parsing.py
notest/lib/utils.py