Metadata-Version: 1.1
Name: notest
Version: 0.1.0
Summary: Not Only Test! One Excellent Python Testing Tool
Home-page: https://github.com/godq/pyresttest
Author: Chuanhao Qu
Author-email: quchuanhao@gmail.com
License: Apache License, Version 2.0
Keywords: rest,web,http,testing,notest,api
Platform: UNKNOWN
Classifier: Environment :: Console
Classifier: License :: OSI Approved :: Apache Software License
Classifier: Natural Language :: English
Classifier: Programming Language :: Python :: 3.5
Classifier: Programming Language :: Python :: 3.6
Classifier: Programming Language :: Python :: 3.7
Classifier: Topic :: Software Development :: Testing
Classifier: Topic :: Software Development :: Quality Assurance
Classifier: Topic :: Utilities
